yorkshire/__about__.py
yorkshire/__init__.py
yorkshire/__main__.py
yorkshire/_lib.py
yorkshire/cli.py
yorkshire/exceptions.py
yorkshire-0.0.0.dist-info/LICENSE
yorkshire-0.0.0.dist-info/METADATA
yorkshire-0.0.0.dist-info/WHEEL
yorkshire-0.0.0.dist-info/entry_points.txt
yorkshire-0.0.0.dist-info/top_level.txt
yorkshire-0.0.0.dist-info/RECORD
