Metadata-Version: 2.1
Name: yorkshire
Version: 0.0.0
Summary: Yorkshire is your friend who checks requirements files for a possible dependency confusion.
Home-page: https://github.com/DataDog/yorkshire
Author: Fridolin Pokorny
Author-email: fridolin.pokorny@datadoghq.com
Maintainer: Fridolin Pokorny
Maintainer-email: fridolin.pokorny@datadoghq.com
License: Apache-2.0
Download-URL: https://github.com/DataDog/yorkshire
Keywords: packaging,pip,dependencies,dependency-management,utilities,dependency-confusion,guarddog
Platform: UNKNOWN
Classifier: Development Status :: 3 - Alpha
Classifier: Intended Audience :: Developers
Classifier: License :: OSI Approved :: Apache Software License
Classifier: Programming Language :: Python
Classifier: Programming Language :: Python :: 3.8
Classifier: Programming Language :: Python :: 3.9
Classifier: Programming Language :: Python :: 3.10
Classifier: Programming Language :: Python :: 3.11
Classifier: Programming Language :: Python :: Implementation :: CPython
Requires-Python: >=3.8
Requires-Dist: attrs
Requires-Dist: click
Requires-Dist: daiquiri
Requires-Dist: pip
Requires-Dist: pip-requirements-parser
Requires-Dist: requests
Requires-Dist: rich-click
Requires-Dist: tomli
